FastCT/CT.py
FastCT/FastCT.py
FastCT/__init__.py
FastCT-0.0.1.dist-info/LICENSE
FastCT-0.0.1.dist-info/METADATA
FastCT-0.0.1.dist-info/WHEEL
FastCT-0.0.1.dist-info/top_level.txt
FastCT-0.0.1.dist-info/RECORD
