Metadata-Version: 2.1
Name: FastCT
Version: 0.0.1
Summary: CT scan and Radon transform
Home-page: https://github.com/tt-nakamura/CT
Author: Takahiro Nakamura
Author-email: a41757@gmail.com
License: UNKNOWN
Project-URL: Bug Tracker, https://github.com/tt-nakamura/CT/issues
Platform: UNKNOWN
Classifier: Programming Language :: Python :: 3
Classifier: License :: OSI Approved :: MIT License
Classifier: Operating System :: OS Independent
Requires-Python: >=3.6
License-File: LICENSE
